<?xml version="1.0" encoding="UTF-8"?> 
<java version="1.6.0_23" class="java.beans.XMLDecoder"> 
 <object class="java.util.HashMap"> 
  <void method="put"> 
   <string>jTabbedPane1/log_tab_pane/JPanel1/JSplitPane0/MainWindow/null.contentPane/null.layeredPane/JRootPane0/mainFrame</string> 
   <object class="org.jdesktop.application.SessionStorage$TabbedPaneState"> 
    <void property="selectedIndex"> 
     <int>0</int> 
    </void> 
    <void property="tabCount"> 
     <int>3</int> 
    </void> 
   </object> 
  </void> 
  <void method="put"> 
   <string>mainFrame</string> 
   <object class="org.jdesktop.application.SessionStorage$WindowState"> 
    <void property="bounds"> 
     <object class="java.awt.Rectangle"> 
      <int>451</int> 
      <int>79</int> 
      <int>913</int> 
      <int>964</int> 
     </object> 
    </void> 
    <void property="graphicsConfigurationBounds"> 
     <object class="java.awt.Rectangle"> 
      <int>0</int> 
      <int>0</int> 
      <int>1920</int> 
      <int>1200</int> 
     </object> 
    </void> 
    <void property="screenCount"> 
     <int>2</int> 
    </void> 
   </object> 
  </void> 
  <void method="put"> 
   <string>files_table/JViewport0/jScrollPane3/filesPanel/centerPanel/Flash: ROM_ctrl/MainTabbedPane/JPanel0/JSplitPane0/MainWindow/null.contentPane/null.layeredPane/JRootPane0/mainFrame</string> 
   <object class="org.jdesktop.application.SessionStorage$TableState"> 
    <void property="columnWidths"> 
     <array class="int" length="3"> 
      <void index="0"> 
       <int>471</int> 
      </void> 
      <void index="1"> 
       <int>147</int> 
      </void> 
      <void index="2"> 
       <int>146</int> 
      </void> 
     </array> 
    </void> 
   </object> 
  </void> 
  <void method="put"> 
   <string>MainTabbedPane/JPanel0/JSplitPane0/MainWindow/null.contentPane/null.layeredPane/JRootPane0/mainFrame</string> 
   <object class="org.jdesktop.application.SessionStorage$TabbedPaneState"> 
    <void property="selectedIndex"> 
     <int>0</int> 
    </void> 
    <void property="tabCount"> 
     <int>1</int> 
    </void> 
   </object> 
  </void> 
 </object> 
</java> 
